__init__.py
gd_check.py
guardduty_detector_check-0.1.0.dist-info/LICENSE
guardduty_detector_check-0.1.0.dist-info/METADATA
guardduty_detector_check-0.1.0.dist-info/WHEEL
guardduty_detector_check-0.1.0.dist-info/entry_points.txt
guardduty_detector_check-0.1.0.dist-info/top_level.txt
guardduty_detector_check-0.1.0.dist-info/RECORD
