Metadata-Version: 2.1
Name: guardduty-detector-check
Version: 0.1.0
Summary: GuardDuty Detector and Publishing Destination Checker
Author-email: Dustin Whited <dgwhited@gmail.com>
License: Apache License
Project-URL: Repository, https://github.com/dgwhited/guardduty-detector-check
Requires-Python: >=3.9
License-File: LICENSE
Requires-Dist: boto3 >=1.35.43
